nuvem_aws/__init__.py
nuvem_aws/ecs.py
nuvem_aws-0.13.dist-info/LICENSE
nuvem_aws-0.13.dist-info/METADATA
nuvem_aws-0.13.dist-info/WHEEL
nuvem_aws-0.13.dist-info/top_level.txt
nuvem_aws-0.13.dist-info/RECORD
